fundamentus_scraper/__init__.py
fundamentus_scraper/constants.py
fundamentus_scraper/scraper.py
fundamentus_scraper/utils.py
fundamentus_scraper-0.1.0.dist-info/METADATA
fundamentus_scraper-0.1.0.dist-info/WHEEL
fundamentus_scraper-0.1.0.dist-info/top_level.txt
fundamentus_scraper-0.1.0.dist-info/RECORD
