Metadata-Version: 2.1
Name: fundamentus-scraper
Version: 0.1.0
Summary: Web Scraper para dados do Fundamentus
Home-page: https://github.com/seuusuario/fundamentus-scraper
Author: Seu Nome
Author-email: seu@email.com
Classifier: Programming Language :: Python :: 3
Classifier: License :: OSI Approved :: MIT License
Classifier: Operating System :: OS Independent
Requires-Python: >=3.6
Requires-Dist: requests>=2.25.1
Requires-Dist: beautifulsoup4>=4.9.3
Requires-Dist: pandas>=1.2.0
Requires-Dist: openpyxl>=3.0.7
